mfd_const/__init__.py
mfd_const/_internal_data_structures.py
mfd_const/mfd_const.py
mfd_const/network.py
mfd_const/qos.py
mfd_const/release.py
mfd_const-0.24.0.dist-info/licenses/AUTHORS.md
mfd_const-0.24.0.dist-info/licenses/LICENSE.md
mfd_const-0.24.0.dist-info/METADATA
mfd_const-0.24.0.dist-info/WHEEL
mfd_const-0.24.0.dist-info/top_level.txt
mfd_const-0.24.0.dist-info/RECORD
