Metadata-Version: 2.4
Name: mfd-const
Version: 0.24.0
Summary: Module for keeping const values.
Project-URL: Homepage, https://github.com/intel/mfd
Project-URL: Repository, https://github.com/intel/mfd-const
Project-URL: Issues, https://github.com/intel/mfd-const/issues
Project-URL: Changelog, https://github.com/intel/mfd-const/blob/main/CHANGELOG.md
Requires-Python: <3.14,>=3.10
License-File: LICENSE.md
License-File: AUTHORS.md
Requires-Dist: mfd-typing>=1.23
Dynamic: license-file
